{"format":2,"version":"6.2","globals":"4e05ff2cd0df3175c729062d41e72c31","files":{"d_65d7a56a98bc6906___init___py":{"hash":"8f96e0487d400bed7b4c91e861310773","index":{"nums":[0,1,0,0,0,0,0,0],"html_filename":"d_65d7a56a98bc6906___init___py.html","relative_filename":"table_booker/__init__.py"}},"d_65d7a56a98bc6906_admin_py":{"hash":"f24a53970847484bfaa8f57892887c01","index":{"nums":[0,1,21,0,21,0,0,0],"html_filename":"d_65d7a56a98bc6906_admin_py.html","relative_filename":"table_booker/admin.py"}},"d_65d7a56a98bc6906_apps_py":{"hash":"698d6ab6e249a10e7528ce8c6c62b883","index":{"nums":[0,1,4,0,4,0,0,0],"html_filename":"d_65d7a56a98bc6906_apps_py.html","relative_filename":"table_booker/apps.py"}},"d_65d7a56a98bc6906_factories_py":{"hash":"e7278bbf61c6ae01813c176ce0bc6252","index":{"nums":[0,1,46,0,0,0,0,0],"html_filename":"d_65d7a56a98bc6906_factories_py.html","relative_filename":"table_booker/factories.py"}},"d_65d7a56a98bc6906_forms_py":{"hash":"5990b30afd80618ce8be24331eaba856","index":{"nums":[0,1,40,0,1,0,0,0],"html_filename":"d_65d7a56a98bc6906_forms_py.html","relative_filename":"table_booker/forms.py"}},"d_765b5fb958fc4583_0001_initial_py":{"hash":"3cfc0f251e30b0b4d89f9370554c6179","index":{"nums":[0,1,7,0,0,0,0,0],"html_filename":"d_765b5fb958fc4583_0001_initial_py.html","relative_filename":"table_booker/migrations/0001_initial.py"}},"d_765b5fb958fc4583_0002_auto_20210622_1442_py":{"hash":"3108962aa9b7f0064717fd1e2e60cd3a","index":{"nums":[0,1,5,0,0,0,0,0],"html_filename":"d_765b5fb958fc4583_0002_auto_20210622_1442_py.html","relative_filename":"table_booker/migrations/0002_auto_20210622_1442.py"}},"d_765b5fb958fc4583___init___py":{"hash":"3c77fc9ef7f887ac2508d4109cf92472","index":{"nums":[0,1,0,0,0,0,0,0],"html_filename":"d_765b5fb958fc4583___init___py.html","relative_filename":"table_booker/migrations/__init__.py"}},"d_65d7a56a98bc6906_models_py":{"hash":"abfdc54b0724d506022298bf7ee86979","index":{"nums":[0,1,43,0,41,0,0,0],"html_filename":"d_65d7a56a98bc6906_models_py.html","relative_filename":"table_booker/models.py"}},"d_65d7a56a98bc6906_urls_py":{"hash":"3cb0575d89e3e697843f8b8dd5046e86","index":{"nums":[0,1,4,0,0,0,0,0],"html_filename":"d_65d7a56a98bc6906_urls_py.html","relative_filename":"table_booker/urls.py"}},"d_65d7a56a98bc6906_views_py":{"hash":"d4b1aba5f169537a399554c4603bf53c","index":{"nums":[0,1,87,0,1,0,0,0],"html_filename":"d_65d7a56a98bc6906_views_py.html","relative_filename":"table_booker/views.py"}}}}